dist_watchtower/.DS_Store
dist_watchtower/assets/AboutView.23c521d7.css
dist_watchtower/assets/AboutView.db330516.js
dist_watchtower/assets/ProjectDetailView.707dcf7c.js
dist_watchtower/assets/ProjectDetailView.a5b51335.css
dist_watchtower/assets/index.9bb56d0d.css
dist_watchtower/assets/index.e15df5e8.js
dist_watchtower/favicon.ico
dist_watchtower/index.html
dist_watchtower/static/.DS_Store
watchtower_pipeline/__init__.py
watchtower_pipeline/example.py
watchtower_pipeline/ffprobe.py
watchtower_pipeline/kitsu.py
watchtower_pipeline/models.py
watchtower_pipeline/writers.py
watchtower_pipeline-0.1.7.dist-info/WHEEL
watchtower_pipeline-0.1.7.dist-info/METADATA
watchtower_pipeline-0.1.7.dist-info/RECORD
