Metadata-Version: 2.1
Name: watchtower-pipeline
Version: 0.1.7
Summary: Utilities to generate static data for Watchtower.
License: GPL-3.0-or-later
Author: Francesco Siddi
Author-email: francesco@blender.org
Requires-Python: >=3.9,<4.0
Classifier: License :: OSI Approved :: GNU General Public License v3 or later (GPLv3+)
Classifier: Programming Language :: Python :: 3
Classifier: Programming Language :: Python :: 3.10
Classifier: Programming Language :: Python :: 3.9
Requires-Dist: requests (>=2.27.1,<3.0.0)
Requires-Dist: tqdm (>=4.62.3,<5.0.0)
